CLASSIFIERS.txt
LICENSE
MANIFEST.in
README.md
setup.py
contact/__init__.py
contact/admin.py
contact/models.py
django_contact.egg-info/PKG-INFO
django_contact.egg-info/SOURCES.txt
django_contact.egg-info/dependency_links.txt
django_contact.egg-info/not-zip-safe
django_contact.egg-info/requires.txt
django_contact.egg-info/top_level.txt